structure_tensor/__init__.py
structure_tensor/multiprocessing.py
structure_tensor/st2d.py
structure_tensor/st3d.py
structure_tensor/util.py
structure_tensor/cp/__init__.py
structure_tensor/cp/st3dcp.py
structure_tensor-0.3.4.dist-info/licenses/LICENSE
structure_tensor-0.3.4.dist-info/METADATA
structure_tensor-0.3.4.dist-info/WHEEL
structure_tensor-0.3.4.dist-info/top_level.txt
structure_tensor-0.3.4.dist-info/RECORD
