Metadata-Version: 2.4
Name: structure-tensor
Version: 0.3.4
Summary: Fast and simple to use 2D and 3D structure tensor implementation for Python.
Author-email: Niels Jeppesen <niejep@dtu.dk>
License: MIT License
Project-URL: Homepage, https://github.com/Skielex/structure-tensor
Classifier: Development Status :: 3 - Alpha
Classifier: Environment :: Console
Classifier: Intended Audience :: Developers
Classifier: Intended Audience :: Science/Research
Classifier: License :: OSI Approved :: MIT License
Classifier: Natural Language :: English
Classifier: Operating System :: OS Independent
Classifier: Programming Language :: Python
Classifier: Topic :: Scientific/Engineering :: Image Recognition
Classifier: Topic :: Scientific/Engineering :: Artificial Intelligence
Classifier: Topic :: Scientific/Engineering :: Mathematics
Requires-Python: >=3.10
License-File: LICENSE
Requires-Dist: numpy>=1.20
Requires-Dist: scipy>=1.3
Provides-Extra: cupy
Requires-Dist: cupy>=8; extra == "cupy"
Dynamic: license-file
